lll_pricing_calculation/__init__.py
lll_pricing_calculation/openai_pricing_calculation.py
openai_pricing_calc_draft-0.5.0.dist-info/METADATA
openai_pricing_calc_draft-0.5.0.dist-info/WHEEL
openai_pricing_calc_draft-0.5.0.dist-info/top_level.txt
openai_pricing_calc_draft-0.5.0.dist-info/RECORD
