Metadata-Version: 2.1
Name: openai-pricing-calc-draft
Version: 0.5.0
Summary: LLM Cost Calculation
Home-page: https://github.com/kokenconsulting/openai-api-pricing/tree/main/pypi
Author: Koken Consultng
Author-email: <ali@koken-consulting.com>
Keywords: python,video,stream,video stream,camera stream,sockets
Classifier: Development Status :: 1 - Planning
Classifier: Intended Audience :: Developers
Classifier: Programming Language :: Python :: 3
Classifier: Operating System :: Unix
Classifier: Operating System :: MacOS :: MacOS X
Classifier: Operating System :: Microsoft :: Windows
Requires-Dist: requests
